{
  "title": "Show #2184 - Thursday, February 17, 1994",
  "date": {
    "day": 17,
    "month": "February",
    "year": 1994
  },
  "clues": [
    {
      "category": "BODIES OF WATER",
      "text": "This ocean may have been named for a legendary lost continent, or for an African mountain system",
      "answer": "the Atlantic"
    },
    {
      "category": "TV TEENS",
      "text": "Sara Gilbert earned a 1993 Emmy nomination for her role as teenager Darlene Conner on this series",
      "answer": "Roseanne"
    },
    {
      "category": "WEIGHTS & MEASURES",
      "text": "1 of these is equal to 1/2 fluid ounce or 3 teaspoons",
      "answer": "a tablespoon"
    },
    {
      "category": "ANIMALS",
      "text": "The mehari is a special breed of this humped mammal trained for warfare & racing",
      "answer": "a camel"
    },
    {
      "category": "JUST DESSERTS",
      "text": "This dessert has the same name as a 6-8-year-old Girl Scout",
      "answer": "brownie"
    },
    {
      "category": "COMMON BONDS",
      "text": "T,polo,flannel",
      "answer": "shirts"
    },
    {
      "category": "BODIES OF WATER",
      "text": "In area, this Great Lake is the largest body of fresh water in the world",
      "answer": "Lake Superior"
    },
    {
      "category": "TV TEENS",
      "text": "On \"Phenom\" Angela Goethals plays a teenage champ in this sport",
      "answer": "tennis"
    },
    {
      "category": "WEIGHTS & MEASURES",
      "text": "There are 4 gills in a pint & 8 in one of these",
      "answer": "a quart"
    },
    {
      "category": "ANIMALS",
      "text": "It's the most carnivorous of the bears, feeding especially on seals & walrus",
      "answer": "the polar bear"
    },
    {
      "category": "JUST DESSERTS",
      "text": "The islands in floating island are made of this egg white mixture that tops key lime pie",
      "answer": "meringue"
    },
    {
      "category": "COMMON BONDS",
      "text": "Punk,pompadour,pixie",
      "answer": "hairdos"
    },
    {
      "category": "BODIES OF WATER",
      "text": "The Sinai Peninsula divides the northern end of this sea into the gulfs of Aqaba & Suez",
      "answer": "the Red Sea"
    },
    {
      "category": "TV TEENS",
      "text": "This star of \"Cafe Americain\" was once a TV teen on \"One Day at a Time\"",
      "answer": "Valerie Bertinelli"
    },
    {
      "category": "WEIGHTS & MEASURES",
      "text": "1 of these units of length is equal to 3,280.8 feet",
      "answer": "a kilometer"
    },
    {
      "category": "ANIMALS",
      "text": "A young male horse is called a colt, & a young female is called this",
      "answer": "a filly"
    },
    {
      "category": "JUST DESSERTS",
      "text": "It's a thin sheet of sponge cake spread with jam & rolled up",
      "answer": "a jelly roll"
    },
    {
      "category": "COMMON BONDS",
      "text": "Gin,Michigan rummy,hearts",
      "answer": "card games"
    },
    {
      "category": "BODIES OF WATER",
      "text": "A 350-mile-long strait near South America's southern tip was discovered by & named for this explorer",
      "answer": "Magellan"
    },
    {
      "category": "TV TEENS",
      "text": "Danica McKellar played Kevin's true love Winnie on this series set in the '60s",
      "answer": "The Wonder Years"
    },
    {
      "category": "WEIGHTS & MEASURES",
      "text": "This country abandoned the metric system in 1812 & readopted it in 1840",
      "answer": "France"
    },
    {
      "category": "ANIMALS",
      "text": "Named for a region of Russia, it's the largest of all wild cats",
      "answer": "the Siberian tiger"
    },
    {
      "category": "JUST DESSERTS",
      "text": "In the dessert version of fondue, cake & fruit are dipped into this melted substance",
      "answer": "chocolate"
    },
    {
      "category": "COMMON BONDS",
      "text": "Potter's,spinning,steering",
      "answer": "types of wheels"
    },
    {
      "category": "BODIES OF WATER",
      "text": "The Hanseatic League once controlled commerce on this sea that borders Germany & Poland",
      "answer": "the Baltic Sea"
    },
    {
      "category": "TV TEENS",
      "text": "It's the numerical name of the teenager played by Jenna von Oy on \"Blossom\"",
      "answer": "Six"
    },
    {
      "category": "WEIGHTS & MEASURES",
      "text": "The pennyweight is a unit in this system used to measure precious metals",
      "answer": "the troy system"
    },
    {
      "category": "ANIMALS",
      "text": "The only 2 species of eagles found in the U.S. are the bald & this colorful variety",
      "answer": "the golden eagle"
    },
    {
      "category": "JUST DESSERTS",
      "text": "This dark liquid is the traditional sweetening of Indian pudding",
      "answer": "molasses"
    },
    {
      "category": "COMMON BONDS",
      "text": "Krone,colon,quetzal",
      "answer": "monies"
    },
    {
      "category": "WORLD HISTORY",
      "text": "From 1947-49 Pakistan fought this country in the first of 3 conflicts over the state of Kashmir",
      "answer": "India"
    },
    {
      "category": "ISLANDS",
      "text": "In Danish this island is known as Gronland",
      "answer": "Greenland"
    },
    {
      "category": "MUSICAL INSTRUMENTS",
      "text": "Because of its limited range, military calls on this instrument usually use only 4 or 5 notes",
      "answer": "the bugle"
    },
    {
      "category": "SPANISH CLASS",
      "text": "It's Spanish for mister",
      "answer": "señor"
    },
    {
      "category": "LITERATURE",
      "text": "Dostoyevsky's book about these title brothers is considered his masterpiece",
      "answer": "The Brothers Karamazov"
    },
    {
      "category": "BENJAMIN FRANKLIN",
      "text": "Before Jane Fonda, Ben deduced there's more exercise going up & down these than straight walking",
      "answer": "stairs"
    },
    {
      "category": "WORLD HISTORY",
      "text": "In 1502 he succeeded his uncle Ahuitzotl as emperor of the Aztecs",
      "answer": "Montezuma"
    },
    {
      "category": "ISLANDS",
      "text": "Unimak is the closest island to Alaska in this chain",
      "answer": "the Aleutians"
    },
    {
      "category": "MUSICAL INSTRUMENTS",
      "text": "A large one of these instruments may have over 5,000 pipes",
      "answer": "the organ"
    },
    {
      "category": "SPANISH CLASS",
      "text": "Topaz is topacio, while this gem is zafiro",
      "answer": "sapphire"
    },
    {
      "category": "LITERATURE",
      "text": "An ex-preacher named Jim Casy accompanies the Joads to California in this Steinbeck novel",
      "answer": "The Grapes of Wrath"
    },
    {
      "category": "BENJAMIN FRANKLIN",
      "text": "As a member of a society that formed to do this, Franklin had to have a number of leather   buckets ready",
      "answer": "put out fires"
    },
    {
      "category": "WORLD HISTORY",
      "text": "In December 1809 this emperor divorced his first wife; 4 months later he married Archduchess Marie-Louise",
      "answer": "Napoleon"
    },
    {
      "category": "ISLANDS",
      "text": "The southwest coast of this Italian island is only about 90 miles from Cape Bon in Tunisia",
      "answer": "Sicily"
    },
    {
      "category": "MUSICAL INSTRUMENTS",
      "text": "The full name of this instrument is Italian for \"small flute\"",
      "answer": "the piccolo"
    },
    {
      "category": "SPANISH CLASS",
      "text": "This season of the year is la primavera",
      "answer": "spring"
    },
    {
      "category": "LITERATURE",
      "text": "This author of \"The Age of Innocence\" also wrote some ghost stories",
      "answer": "Edith Wharton"
    },
    {
      "category": "BENJAMIN FRANKLIN",
      "text": "Franklin said that this device also worked on the top of ships' masts with a wire to the water",
      "answer": "the lightning rod"
    },
    {
      "category": "WORLD HISTORY",
      "text": "For about 2,350 years the kingdom of Cush flourished along the Nile River in this country south of Egvpt",
      "answer": "Sudan"
    },
    {
      "category": "ISLANDS",
      "text": "From independence in 1960 until 1975, this island country was known as the Malagasy Republic",
      "answer": "Madagascar"
    },
    {
      "category": "MUSICAL INSTRUMENTS",
      "text": "The name tuba comes from the Latin for this smaller brass instrument",
      "answer": "the trumpet"
    },
    {
      "category": "SPANISH CLASS",
      "text": "Gracias means \"thank you\", & this means \"thank you very much\"",
      "answer": "muchas gracias"
    },
    {
      "category": "LITERATURE",
      "text": "\"The Troll Garden\" was the first collection of stories by this author of \"O Pioneers!\"",
      "answer": "Willa Cather"
    },
    {
      "category": "BENJAMIN FRANKLIN",
      "text": "Ben felt this \"most ancient...game known among men\" could teach foresight & caution",
      "answer": "chess"
    },
    {
      "category": "WORLD HISTORY",
      "text": "In 1986 explosions & fire shut down a nuclear power plant near Chernobyl in this Soviet republic",
      "answer": "the Ukraine"
    },
    {
      "category": "ISLANDS",
      "text": "The island of Isabela constitutes more than half of the land area of this Ecuadorean archipelago",
      "answer": "the Galapagos Islands"
    },
    {
      "category": "MUSICAL INSTRUMENTS",
      "text": "Over 600 of his violins survive, including one he made in 1716 called \"The Messiah\"",
      "answer": "Stradivarius"
    },
    {
      "category": "SPANISH CLASS",
      "text": "This liquid is known as agua caliente; if you get in trouble, you're in it",
      "answer": "hot water"
    },
    {
      "category": "LITERATURE",
      "text": "His 1874 novel \"Far From the Madding Crowd\" begins with a description of farmer Oak",
      "answer": "Thomas Hardy"
    },
    {
      "category": "BENJAMIN FRANKLIN",
      "text": "Poor Richard's last name",
      "answer": "Saunders"
    }
  ]
}