{
  "title": "Show #7816 - Monday, September 10, 2018",
  "date": {
    "day": 10,
    "month": "September",
    "year": 2018
  },
  "clues": [
    {
      "category": "US OPEN 50 YEARS",
      "text": "In 1968, the first Open men's singles winner wasthisathlete & activist, whose name is now on the Open's main stadium",
      "answer": "Arthur Ashe"
    },
    {
      "category": "EXERCISING: YOUR OPTIONS",
      "text": "Take a run at this exercise machine, also defined as \"any monotonous...routine in which there is little or no...progress\"",
      "answer": "a treadmill"
    },
    {
      "category": "FAMOUS THREESOMES",
      "text": "Moe, Larry & Curly",
      "answer": "the Three Stooges"
    },
    {
      "category": "IN\" THE DICTIONARY",
      "text": "They're what an entomologist studies",
      "answer": "insects"
    },
    {
      "category": "HIS WIDOW LIVED ON",
      "text": "Zee James was this outlaw's fiancee for 9 years & his widow for 18, both longer than her marriage",
      "answer": "Jesse James"
    },
    {
      "category": "OUR STATE LOOKS UP TO YOU",
      "text": "Kansas looks up to it",
      "answer": "Nebraska"
    },
    {
      "category": "US OPEN 50 YEARS",
      "text": "In 1973Ms. Court & Mr. Newcombegot $25,000 each as the U.S. Open was the first of this quartet of titles to equalize men's & women'sprizes",
      "answer": "the Grand Slam"
    },
    {
      "category": "EXERCISING: YOUR OPTIONS",
      "text": "A 150-lb. woman can burn 90 calories in 10 mins. doing this alliterative exercise using leaping & clapping hands repeatedly",
      "answer": "jumping jacks"
    },
    {
      "category": "FAMOUS THREESOMES",
      "text": "In a Mother Goose rhyme, \"Rub-a-dub-dub\", they're the \"three men in a tub\"",
      "answer": "the butcher, the baker and the candlestick maker"
    },
    {
      "category": "IN\" THE DICTIONARY",
      "text": "Depending on how you pronounce it, it can mean to hint at, or very personal & private",
      "answer": "intimate"
    },
    {
      "category": "HIS WIDOW LIVED ON",
      "text": "In 2018 this widow of a Beatle turned 85 & voiced a role in the movie \"Isle of Dogs\"",
      "answer": "Yoko Ono"
    },
    {
      "category": "OUR STATE LOOKS UP TO YOU",
      "text": "It's due north of New Mexico",
      "answer": "Colorado"
    },
    {
      "category": "US OPEN 50 YEARS",
      "text": "With a powerful style of play,shewon the women's singles in the1990s, 2000s & 2010s, the only player to do so",
      "answer": "Serena Williams"
    },
    {
      "category": "EXERCISING: YOUR OPTIONS",
      "text": "Sign up for this 4-letter Hindu philosophy; \"The Onion\" had an Ali-like \"champion\" of it boast, \"I am the serenest!\"",
      "answer": "yoga"
    },
    {
      "category": "FAMOUS THREESOMES",
      "text": "A legendary love triangle consisted of King Arthur, Queen Guinevere & him",
      "answer": "Lancelot"
    },
    {
      "category": "IN\" THE DICTIONARY",
      "text": "In her \"I Am Woman\" song, Helen Reddy was strong & she was this, meaning she can't be defeated",
      "answer": "invincible"
    },
    {
      "category": "HIS WIDOW LIVED ON",
      "text": "Valerie (nee Fletcher) spent 47 years as this poet's widow & cashed more than a few \"Cats\" checks",
      "answer": "(T.S.) Eliot"
    },
    {
      "category": "OUR STATE LOOKS UP TO YOU",
      "text": "Iowans roll their eyes upward at this state",
      "answer": "Minnesota"
    },
    {
      "category": "US OPEN 50 YEARS",
      "text": "The 1990 Open heralded a new all-time great when, at 19,hebeat Agassi to become the youngest men's singles champ",
      "answer": "(Pete) Sampras"
    },
    {
      "category": "EXERCISING: YOUR OPTIONS",
      "text": "Tighten & hold your pelvic floor muscles for 5 seconds, 5 times in these not-just-for-pregnancy exercises",
      "answer": "kegels"
    },
    {
      "category": "FAMOUS THREESOMES",
      "text": "Their names are Melchior, Balthasar & Gaspar",
      "answer": "the three wise men (or the Magi)"
    },
    {
      "category": "IN\" THE DICTIONARY",
      "text": "Eggs can be artificially hatched in one type of this apparatus; premature babies are kept in another type",
      "answer": "an incubator"
    },
    {
      "category": "HIS WIDOW LIVED ON",
      "text": "This composer died in 1791; his widow Constanze lived until 1842 & there are even purported photos of her",
      "answer": "Mozart"
    },
    {
      "category": "OUR STATE LOOKS UP TO YOU",
      "text": "It's Arkansas' good neighbor to the north",
      "answer": "Missouri"
    },
    {
      "category": "US OPEN 50 YEARS",
      "text": "Hisdominance of the first decade of the 2000s includes an Open Era record of five straight titles, losing two sets in the five finals",
      "answer": "(Roger) Federer"
    },
    {
      "category": "EXERCISING: YOUR OPTIONS",
      "text": "Dude, time to hit the exercise machine & do this pulldown, named for the widest muscle in your back!",
      "answer": "the latissimus"
    },
    {
      "category": "FAMOUS THREESOMES",
      "text": "The Three Tenors were Pavarotti, Domingo &thisman, who is on an extended farewell tour",
      "answer": "José Carreras"
    },
    {
      "category": "IN\" THE DICTIONARY",
      "text": "This 10-letter adjective describes certain devices that cause or are designed to cause fires",
      "answer": "incendiary"
    },
    {
      "category": "HIS WIDOW LIVED ON",
      "text": "In a 2012 memoir the widow of this Argentine-born guerrilla fighter tells of how he declared his love for her in a Jeep",
      "answer": "(Che) Guevara"
    },
    {
      "category": "OUR STATE LOOKS UP TO YOU",
      "text": "It's the state Wyoming looks up to",
      "answer": "Montana"
    },
    {
      "category": "BACK TO BASICS",
      "text": "This word for \"basic\" is also a 3rd grade type of school",
      "answer": "primary (or elementary)"
    },
    {
      "category": "BUSINESS",
      "text": "This 3-letter memorandum of debt is a strong but not legally binding promise to pay",
      "answer": "I.O.U."
    },
    {
      "category": "THE MOVIES",
      "text": "Bob Parr stays home taking care of the kids while Elastigirl is out saving the world in this 2018 sequel",
      "answer": "Incredibles 2"
    },
    {
      "category": "LITERATURE",
      "text": "In this H.G. Wells classic, the narrator is \"drawn on by the...Earth's fate\" & sees it in \"strides of a thousand years\"",
      "answer": "The Time Machine"
    },
    {
      "category": "COLLEGES EAST OF THE MISSISSIPPI FROM K TO Q",
      "text": "You're always part of the Wolfpack at this Raleigh school",
      "answer": "NC State"
    },
    {
      "category": "BACK TO BASICS",
      "text": "RIF, short for \"Reading is\" this, has aided children's literacy since 1966",
      "answer": "fundamental"
    },
    {
      "category": "HISTORY",
      "text": "The first capital of California following American occupation in 1846 was this city, today the \"capital\" of Silicon Valley",
      "answer": "San Jose"
    },
    {
      "category": "BUSINESS",
      "text": "In 2007 Forbes reported that this TV personality was \"America's sole black female billionaire\"",
      "answer": "Oprah Winfrey"
    },
    {
      "category": "THE MOVIES",
      "text": "A mute Sally Hawkins falls in love with an amphibious creature in this 2017 movie, Oscar's Best Picture",
      "answer": "The Shape of Water"
    },
    {
      "category": "LITERATURE",
      "text": "Oddly, the protagonist of \"The Tin Drum\" stops doing this at age 3",
      "answer": "growing"
    },
    {
      "category": "COLLEGES EAST OF THE MISSISSIPPI FROM K TO Q",
      "text": "It's about a 50-mile drive from Penn to this other Ivy League school that fits the category",
      "answer": "Princeton"
    },
    {
      "category": "BACK TO BASICS",
      "text": "The timeless line \"when in doubt, go basic\" this appeared in a 2017 Vogue feature",
      "answer": "black"
    },
    {
      "category": "HISTORY",
      "text": "Last name of the young family seenherecirca 1920--father & daughter would combine to serve 31 years as prime minister of India",
      "answer": "Nehru"
    },
    {
      "category": "BUSINESS",
      "text": "After a $26 billion merger in 2016, this business website might keep nagging Microsoft to update its resume",
      "answer": "LinkedIn"
    },
    {
      "category": "THE MOVIES",
      "text": "Gloria Swanson utters the immortal line \"I am big, it's the pictures that got small\" in this classic film",
      "answer": "Sunset Boulevard"
    },
    {
      "category": "LITERATURE",
      "text": "Nicholas Rubashov is a revolutionary caught up in this leader's purges in Arthur Koestler's \"Darkness at Noon\"",
      "answer": "Stalin"
    },
    {
      "category": "COLLEGES EAST OF THE MISSISSIPPI FROM K TO Q",
      "text": "Neil Armstrong took more than one small step for himself attending this Big Ten university in Indiana",
      "answer": "Purdue"
    },
    {
      "category": "BACK TO BASICS",
      "text": "\"Watery\" term for the dominant trend, perhaps describing big media",
      "answer": "mainstream"
    },
    {
      "category": "HISTORY",
      "text": "2-word Latin term for the period of relative peace ending with the death of Marcus Aurelius",
      "answer": "Pax Romana"
    },
    {
      "category": "BUSINESS",
      "text": "A passage from the book of Hosea was the inspiration Israel's first Minister of Transportation had for naming this airline",
      "answer": "El Al"
    },
    {
      "category": "THE MOVIES",
      "text": "\"The Disaster Artist\" chronicles Tommy Wiseau making this so-bad-it's-good film",
      "answer": "The Room"
    },
    {
      "category": "LITERATURE",
      "text": "Booth Tarkington's novel about this \"Magnificent\" family documents their decline",
      "answer": "the Ambersons"
    },
    {
      "category": "COLLEGES EAST OF THE MISSISSIPPI FROM K TO Q",
      "text": "About 2,000 women attend this college in South Hadley, Mass., one of the Seven Sisters schools",
      "answer": "Mount Holyoke"
    },
    {
      "category": "BACK TO BASICS",
      "text": "\"R\" you ready? This 11-letter word means \"basic\", like skills everyone should have",
      "answer": "rudimentary"
    },
    {
      "category": "HISTORY",
      "text": "3 pretenders to the Russian throne known as \"false\" this name plagued the Time of Troubles in the early 1600s",
      "answer": "the false Dimitrys"
    },
    {
      "category": "BUSINESS",
      "text": "Corn is traded at this sort of exchange as well as, of course, frozen concentrated orange juice",
      "answer": "commodity"
    },
    {
      "category": "THE MOVIES",
      "text": "A 12-year-old Jodie Foster played a prostitute opposite Robert De Niro in this 1976 film",
      "answer": "Taxi Driver"
    },
    {
      "category": "LITERATURE",
      "text": "In a Saul Bellow novel, Eugene Henderson gets this sacred title from the African Wariri tribe",
      "answer": "the Rain King"
    },
    {
      "category": "COLLEGES EAST OF THE MISSISSIPPI FROM K TO Q",
      "text": "Let's take a poll--does at least one of you 3 know this \"Q\" university is in Hamden, Connecticut?",
      "answer": "Quinnipiac"
    }
  ]
}