{
  "title": "Show #4151 - Monday, September 23, 2002",
  "date": {
    "day": 23,
    "month": "September",
    "year": 2002
  },
  "clues": [
    {
      "category": "MUSICAL MATTERS",
      "text": "At age 14 Wynton Marsalis performed Haydn's concerto for this instrument",
      "answer": "trumpet"
    },
    {
      "category": "HORSE TALK",
      "text": "In the 1932 film \"Horse Feathers\", he remarked, \"I'd horsewhip you if I had a horse\"",
      "answer": "Groucho Marx"
    },
    {
      "category": "SPANISH CLASS",
      "text": "This farm animal is una vaca",
      "answer": "cow"
    },
    {
      "category": "CLASSIC FILMS IN OTHER WORDS",
      "text": "1990:\"Jigs Accompanied by Lupine Creatures\"",
      "answer": "Dances with Wolves"
    },
    {
      "category": "WHAT GRADE DID YOU GET?",
      "text": "Anthracite, the highest grade of this, is made almost entirely of carbon",
      "answer": "coal"
    },
    {
      "category": "AN \"F\" IN HISTORY",
      "text": "Soon after Ataturk became Turkey's president in 1923, he banned the wearing of this traditional hat",
      "answer": "fez"
    },
    {
      "category": "MUSICAL MATTERS",
      "text": "The Dixie Chicks' first CD had the rhyming title \"Thank Heavens for\" this TV cowgirl",
      "answer": "Dale Evans"
    },
    {
      "category": "HORSE TALK",
      "text": "On Oct. 19, 1924 Grantland Rice wrote that \"Their real names are Stuhldreher, Miller, Crowley, and Leyden\"",
      "answer": "\"Four Horsemen of Notre Dame\""
    },
    {
      "category": "SPANISH CLASS",
      "text": "You can find libros at una libreria y una biblioteca, these 2 related places",
      "answer": "library & bookstore"
    },
    {
      "category": "CLASSIC FILMS IN OTHER WORDS",
      "text": "1957:\"One Dozen Ticked-Off Dudes\"",
      "answer": "12 Angry Men"
    },
    {
      "category": "WHAT GRADE DID YOU GET?",
      "text": "Grades of this potable range from doux to brut",
      "answer": "champagne"
    },
    {
      "category": "AN \"F\" IN HISTORY",
      "text": "He founded Philly's first police force",
      "answer": "Ben Franklin"
    },
    {
      "category": "MUSICAL MATTERS",
      "text": "It sounds like a small trench around a castle, but it was the major type of late medieval composition",
      "answer": "motet"
    },
    {
      "category": "HORSE TALK",
      "text": "\"For want of a nail the shoe is lost, for want of a shoe the horse is lost, for want of a horse\" this \"is lost\"",
      "answer": "the rider"
    },
    {
      "category": "SPANISH CLASS",
      "text": "This color is azul",
      "answer": "blue"
    },
    {
      "category": "CLASSIC FILMS IN OTHER WORDS",
      "text": "1969:\"12 O'Clock Herdsman\"",
      "answer": "Midnight Cowboy"
    },
    {
      "category": "WHAT GRADE DID YOU GET?",
      "text": "A \"less than investment grade\" bond is usually referred to as this 4-letter term",
      "answer": "junk"
    },
    {
      "category": "AN \"F\" IN HISTORY",
      "text": "The longest currently serving leader in the Western Hemisphere; he started in 1959",
      "answer": "Fidel Castro"
    },
    {
      "category": "MUSICAL MATTERS",
      "text": "The 19th century composer of the following, he basically wrote for only one instrument",
      "answer": "Frederic Chopin"
    },
    {
      "category": "HORSE TALK",
      "text": "Dr. Johnson called it \"A grain which in England is generally given to horses, but in Scotland supports the people\"",
      "answer": "oats"
    },
    {
      "category": "SPANISH CLASS",
      "text": "The word \"alligator\" comes from the Spanish el lagarto, this reptile",
      "answer": "lizard"
    },
    {
      "category": "CLASSIC FILMS IN OTHER WORDS",
      "text": "1973:\"Final Argentine Dance on the Banks of the Seine\"",
      "answer": "Last Tango in Paris"
    },
    {
      "category": "WHAT GRADE DID YOU GET?",
      "text": "Bond & book are grades of this product made from compressed cellulose",
      "answer": "paper"
    },
    {
      "category": "AN \"F\" IN HISTORY",
      "text": "In 1976 Bob Dole was his running mate",
      "answer": "Gerald Ford"
    },
    {
      "category": "MUSICAL MATTERS",
      "text": "James Blake, who wrote the song \"I'm Just Wild About Harry\", was better known by this nickname",
      "answer": "Eubie"
    },
    {
      "category": "HORSE TALK",
      "text": "An old cliche says a difference of opinion is \"what makes\" these",
      "answer": "horse races"
    },
    {
      "category": "SPANISH CLASS",
      "text": "For spice, you use picante for this adjective; for climate, calido; for temperature, caliente",
      "answer": "hot"
    },
    {
      "category": "CLASSIC FILMS IN OTHER WORDS",
      "text": "1992:\"Primal Impulse\"",
      "answer": "Basic Instinct"
    },
    {
      "category": "WHAT GRADE DID YOU GET?",
      "text": "Excelso is a grade of coffee from this country, perhaps from Medellin",
      "answer": "Colombia"
    },
    {
      "category": "AN \"F\" IN HISTORY",
      "text": "It's the other political party that, like the Whigs, elected only 2 U.S. presidents",
      "answer": "Federalists"
    },
    {
      "category": "CITY WALK",
      "text": "With a current population of 323,000 this North American national capital was founded in the early 1800s",
      "answer": "Ottawa, Canada"
    },
    {
      "category": "NO. 1 IN THE NFL DRAFT",
      "text": "1989 by Dallas:this Bruin, seen here",
      "answer": "Troy Aikman"
    },
    {
      "category": "CONTEMPORARY THEATRE",
      "text": "In 1998, more than a century after that incident with an ax, this accused murderess got her own musical",
      "answer": "Lizzie Borden"
    },
    {
      "category": "THE WRIGHT STUFF",
      "text": "The Wright Brothers made almost 1,000 successful glider flights on a beach near this N.C. town in 1902",
      "answer": "Kitty Hawk"
    },
    {
      "category": "BODY PARTS",
      "text": "A fighter might \"take it on\" this body part without flinching",
      "answer": "the chin"
    },
    {
      "category": "ODD WORDS",
      "text": "This synonym for gibberish comes from the name of a Lewis Carroll poem",
      "answer": "jabberwocky"
    },
    {
      "category": "CITY WALK",
      "text": "The 1,000-year-old Al-Azhar University in this Middle East capital is an important center of Islamic learning",
      "answer": "Cairo, Egypt"
    },
    {
      "category": "NO. 1 IN THE NFL DRAFT",
      "text": "1978 by Houston:this Texas running back",
      "answer": "Earl Campbell"
    },
    {
      "category": "CONTEMPORARY THEATRE",
      "text": "The 2001 play \"Snatches\" depicts snatches of phone conversations between Monica Lewinsky & this former friend",
      "answer": "Linda Tripp"
    },
    {
      "category": "THE WRIGHT STUFF",
      "text": "He designed the Imperial Hotel to withstand Tokyo's earthquakes; in 1923, it was one of the few buildings that did",
      "answer": "Frank Lloyd Wright"
    },
    {
      "category": "BODY PARTS",
      "text": "Some of these have been dubbed middle, little or ring",
      "answer": "fingers"
    },
    {
      "category": "ODD WORDS",
      "text": "A heptastich is a poem or stanza of this many lines",
      "answer": "7"
    },
    {
      "category": "CITY WALK",
      "text": "(Sofia of the Clue Crew reports from Miami.)  Stretching from about 17th Avenue to 37th Avenue is this \"small\" area of Miami",
      "answer": "\"Little Havana\""
    },
    {
      "category": "NO. 1 IN THE NFL DRAFT",
      "text": "1993 by New England:this quarterback",
      "answer": "Drew Bledsoe"
    },
    {
      "category": "CONTEMPORARY THEATRE",
      "text": "In 2001 Marlo Thomas got all dolled up to play this \"Valley of the Dolls\" author in the play \"Paper Doll\"",
      "answer": "Jacqueline Susann"
    },
    {
      "category": "THE WRIGHT STUFF",
      "text": "In 1986 this Texan became House majority leader, succeeding Tip O'Neill",
      "answer": "Jim Wright"
    },
    {
      "category": "BODY PARTS",
      "text": "This long & winding portion of the alimentary canal is divided into small & large sections",
      "answer": "intestines"
    },
    {
      "category": "ODD WORDS",
      "text": "Animal, vegetable or mineral: what kohlrabi is",
      "answer": "vegetable"
    },
    {
      "category": "CITY WALK",
      "text": "Pensione Erdarelli & the Hotel Hassler are both found in this capital city",
      "answer": "Rome, Italy"
    },
    {
      "category": "NO. 1 IN THE NFL DRAFT",
      "text": "1998 by this team:Peyton Manning",
      "answer": "Indianapolis Colts"
    },
    {
      "category": "CONTEMPORARY THEATRE",
      "text": "Bob Gaudio of the 4 Seasons wrote the music for a new musical based on this Kathleen Turner-Nicolas Cage film",
      "answer": "Peggy Sue Got Married"
    },
    {
      "category": "THE WRIGHT STUFF",
      "text": "Benjamin Wright, & not a mule named Sal, was chief engineer for the construction of this waterway from 1817 to 1825",
      "answer": "Erie Canal"
    },
    {
      "category": "BODY PARTS",
      "text": "12 of these 33 bones are thoracic",
      "answer": "vertebrae"
    },
    {
      "category": "ODD WORDS",
      "text": "This word that rhymes with rough is used for the skin of a snake that's been cast off",
      "answer": "slough"
    },
    {
      "category": "CITY WALK",
      "text": "You'll find the Kenyatta Conference Center in this Kenyan city, one of Africa's largest & fastest growing",
      "answer": "Nairobi"
    },
    {
      "category": "NO. 1 IN THE NFL DRAFT",
      "text": "1949 by Philadelphia:this man, \"Concrete Charlie\", the NFL's last 60-minute player",
      "answer": "Chuck Bednarik"
    },
    {
      "category": "CONTEMPORARY THEATRE",
      "text": "John Cullum of \"Northern Exposure\" got more Broadway exposure as a toilet tycoon in this hit musical",
      "answer": "Urinetown"
    },
    {
      "category": "THE WRIGHT STUFF",
      "text": "A black Chicago youth is victimized by a white-dominated society in this novelist's \"Native Son\"",
      "answer": "Richard Wright"
    },
    {
      "category": "BODY PARTS",
      "text": "This shoulder muscle is ready when you are",
      "answer": "deltoid muscle"
    },
    {
      "category": "ODD WORDS",
      "text": "Pandiculation is the act of yawning & doing this, especially first thing in the morning",
      "answer": "stretching"
    }
  ]
}