{
  "title": "Show #4152 - Tuesday, September 24, 2002",
  "date": {
    "day": 24,
    "month": "September",
    "year": 2002
  },
  "clues": [
    {
      "category": "THE U.S.",
      "text": "The highest & northernmost points in the U.S. are in this state",
      "answer": "Alaska"
    },
    {
      "category": "FOOD FOR THOUGHT",
      "text": "These snack \"nuts\" bear the name of a vegetable that also grows in a pod",
      "answer": "peanuts"
    },
    {
      "category": "WHO PLAYED 'EM?",
      "text": "Diarist Bridget Jones",
      "answer": "Renee Zellweger"
    },
    {
      "category": "INVENTED FIRST",
      "text": "Stereoscope,bifocal lens,x-ray tube",
      "answer": "bifocal lens"
    },
    {
      "category": "COME TOGETHER",
      "text": "It's a meeting with the pope, or a group of people attending a TV show taping",
      "answer": "audience"
    },
    {
      "category": "RHYME TIME",
      "text": "Society of Friends member who works as a bread cook",
      "answer": "Quaker baker"
    },
    {
      "category": "THE U.S.",
      "text": "With water covering about 40% of this state's 96,000 square miles of total area, it must have some great lakes",
      "answer": "Michigan"
    },
    {
      "category": "FOOD FOR THOUGHT",
      "text": "(Cheryl of the Clue Crew reports from the Atlanta Zoo)  The wristbones of the giant panda are elongated & act as thumbs for holding stalks of this food, its primary diet",
      "answer": "bamboo"
    },
    {
      "category": "WHO PLAYED 'EM?",
      "text": "Hack screenwriter Joe Gillis, who ends up living & dying on Sunset Blvd.",
      "answer": "William Holden"
    },
    {
      "category": "INVENTED FIRST",
      "text": "Microwave oven,fiberglass,frozen food",
      "answer": "frozen food"
    },
    {
      "category": "COME TOGETHER",
      "text": "From the French for \"sitting\", it's a \"medium-sized\" gathering for communicating with the dead",
      "answer": "seance"
    },
    {
      "category": "RHYME TIME",
      "text": "A frightening milk production facility",
      "answer": "scary dairy"
    },
    {
      "category": "THE U.S.",
      "text": "Between 1990 & 2000 this state's population increased 66.3%",
      "answer": "Nevada"
    },
    {
      "category": "FOOD FOR THOUGHT",
      "text": "This bacterial product was dubbed \"milk of eternal life\" when it rejuvenated French king Francis I",
      "answer": "yogurt"
    },
    {
      "category": "WHO PLAYED 'EM?",
      "text": "Ex-Secret Service agent turned bodyguard Frank Farmer",
      "answer": "Kevin Costner"
    },
    {
      "category": "INVENTED FIRST",
      "text": "Gyroscope,stethoscope,telescope",
      "answer": "telescope"
    },
    {
      "category": "COME TOGETHER",
      "text": "It's the famous presidential retreat where Carter, Begin & Sadat got together in 1978",
      "answer": "Camp David"
    },
    {
      "category": "RHYME TIME",
      "text": "An overloaded Corvette",
      "answer": "heavy Chevy"
    },
    {
      "category": "THE U.S.",
      "text": "You'll find the country's lowest ratio of men to women in the Sarasota metro area of this state",
      "answer": "Florida"
    },
    {
      "category": "FOOD FOR THOUGHT",
      "text": "Upton Sinclair's \"The Jungle\" influenced Teddy Roosevelt to help pass this act abbreviated the PFDA",
      "answer": "Pure Food and Drug Act"
    },
    {
      "category": "WHO PLAYED 'EM?",
      "text": "Dying Radcliffe music major Jenny Cavilleri",
      "answer": "Ali MacGraw"
    },
    {
      "category": "INVENTED FIRST",
      "text": "Linoleum,bakelite,aspartame",
      "answer": "linoleum (around 1860)"
    },
    {
      "category": "COME TOGETHER",
      "text": "It's the small hammer used to quiet disturbances at parliamentary functions",
      "answer": "gavel"
    },
    {
      "category": "RHYME TIME",
      "text": "Someone who gorges himself on sheep meat",
      "answer": "mutton glutton"
    },
    {
      "category": "THE U.S.",
      "text": "This state has 2 of the Top 10 busiest airports in the world",
      "answer": "California (San Francisco & LAX)"
    },
    {
      "category": "FOOD FOR THOUGHT",
      "text": "Breeding female Antarctic fur seals rely almost totally on these shrimplike crustaceans for food",
      "answer": "krill"
    },
    {
      "category": "WHO PLAYED 'EM?",
      "text": "Lt. Chris Burnett, a Navy pilot shot down \"Behind Enemy Lines\"",
      "answer": "Owen Wilson"
    },
    {
      "category": "INVENTED FIRST",
      "text": "Bunsen burner,Geiger counter,Leyden jar",
      "answer": "Leyden jar (1745)"
    },
    {
      "category": "COME TOGETHER",
      "text": "A gathering of famous historical people, \"Meeting of Minds\" was an Emmy-winning creation of this comedian",
      "answer": "Steve Allen"
    },
    {
      "category": "RHYME TIME",
      "text": "A defeated Minoan",
      "answer": "beaten Cretan"
    },
    {
      "category": "THE \"US",
      "text": "Step on a rusty nail & you better hope you've had your booster shot for this",
      "answer": "tetanus"
    },
    {
      "category": "LESSER-KNOWN POEMS",
      "text": "This poet's \"La Vita Nuova\" was just a warmup for his \"Divine Comedy\"",
      "answer": "Dante"
    },
    {
      "category": "NAME THE OLYMPIC CITY",
      "text": "1896 summer games(an obvious choice)",
      "answer": "Athens"
    },
    {
      "category": "REPUBLICANS",
      "text": "The book \"Before the Storm\" argues that this man's failed 1964 campaign led to victory for his ideas",
      "answer": "Barry Goldwater"
    },
    {
      "category": "PICK YOUR POISON",
      "text": "The death cup & destroying angels are poisonous ones of these",
      "answer": "mushrooms"
    },
    {
      "category": "OSCAR NIGHT FASHION",
      "text": "Her see-through outfit the night she won for \"Funny Girl\" inspired a few \"On A Clear Day...\" jokes",
      "answer": "Barbra Streisand"
    },
    {
      "category": "THE \"US",
      "text": "In ancient times, it was an elaborate stone coffin fit for a king",
      "answer": "sarcophagus"
    },
    {
      "category": "LESSER-KNOWN POEMS",
      "text": "One of Whittier's many works attacking this begins, \"Our fellow-countrymen in chains!\"",
      "answer": "slavery"
    },
    {
      "category": "NAME THE OLYMPIC CITY",
      "text": "1936 summer games(Marty Glickman was pulled from the U.S. team)",
      "answer": "Berlin"
    },
    {
      "category": "REPUBLICANS",
      "text": "Nevada governor Kenny Guinn is fighting plans to make this mountain a nuclear waste repository",
      "answer": "Yucca Mountain"
    },
    {
      "category": "PICK YOUR POISON",
      "text": "Fatal to Socrates, this foul-smelling plant now grows in the U.S. & can be seen along roadsides",
      "answer": "hemlock"
    },
    {
      "category": "OSCAR NIGHT FASHION",
      "text": "In 2001 this Icelandic singer appeared in a much talked-about swan dress",
      "answer": "Bjork"
    },
    {
      "category": "THE \"US",
      "text": "The Sutlej & Ravi are major tributaries of this river",
      "answer": "Indus"
    },
    {
      "category": "LESSER-KNOWN POEMS",
      "text": "George Herbert's pattern poem about this religious structure is seen here",
      "answer": "altar"
    },
    {
      "category": "NAME THE OLYMPIC CITY",
      "text": "1984 winter games(a war zone in the 1990s)",
      "answer": "Sarajevo"
    },
    {
      "category": "REPUBLICANS",
      "text": "His website says being GOP leader is important but he's first & foremost a senator from Mississippi",
      "answer": "Trent Lott"
    },
    {
      "category": "PICK YOUR POISON",
      "text": "The nonpoisonous tomato & the poisonous belladonna both belong to this family of plants",
      "answer": "nightshade"
    },
    {
      "category": "OSCAR NIGHT FASHION",
      "text": "In 1968 Sammy Davis Jr. was swinging in love beads & this \"Indian\"-style jacket",
      "answer": "Nehru jacket"
    },
    {
      "category": "THE \"US",
      "text": "Based partly on Plutarch's \"Lives\", it's Shakespeare's one-word-title tragedy about an ancient Roman warrior",
      "answer": "Coriolanus"
    },
    {
      "category": "LESSER-KNOWN POEMS",
      "text": "In a poem on this Italian city, Wordsworth wrote, \"She must espouse the everlasting sea\"",
      "answer": "Venice"
    },
    {
      "category": "NAME THE OLYMPIC CITY",
      "text": "1952 summer games(kayakers Wires & Hietanen win homeland gold)",
      "answer": "Helsinki"
    },
    {
      "category": "REPUBLICANS",
      "text": "This current Kentucky senator pitched a perfect game for the Phillies in 1964",
      "answer": "Jim Bunning"
    },
    {
      "category": "PICK YOUR POISON",
      "text": "The leaves of the purple species of this plant contain a powerful poison used to make digitalis",
      "answer": "foxglove"
    },
    {
      "category": "OSCAR NIGHT FASHION",
      "text": "\"Boys Don't Cry\" star seen here in Versace, in 2001",
      "answer": "Hilary Swank"
    },
    {
      "category": "THE \"US",
      "text": "Remember the Titans?  They were cast into this region below Hades by Zeus",
      "answer": "Tartarus"
    },
    {
      "category": "LESSER-KNOWN POEMS",
      "text": "At 21, Shelley wrote a poem about this queen, the subject of a speech in \"Romeo and Juliet\"",
      "answer": "Queen Mab"
    },
    {
      "category": "NAME THE OLYMPIC CITY",
      "text": "1980 winter games(southeast of St. Regis Falls)",
      "answer": "Lake Placid, New York"
    },
    {
      "category": "REPUBLICANS",
      "text": "This early 20th century movie star was named for 19th century GOP leader Roscoe Conkling",
      "answer": "Roscoe \"Fatty\" Arbuckle"
    },
    {
      "category": "PICK YOUR POISON",
      "text": "This weed with poisonous juices gets its name from the first permanent English settlement in North America",
      "answer": "Jimsonweed (Jamestown weed)"
    },
    {
      "category": "OSCAR NIGHT FASHION",
      "text": "\"Boys Don't Cry\" co-star seen here in Yves Saint Laurent, in 2000",
      "answer": "Chloe Sevigny"
    }
  ]
}