{
  "title": "Show #4304 - Thursday, April 24, 2003",
  "date": {
    "day": 24,
    "month": "April",
    "year": 2003
  },
  "clues": [
    {
      "category": "SCIENCE",
      "text": "The leatherback variety of this reptile is one of the few animals that primarily eat jellyfish",
      "answer": "turtle/tortoise"
    },
    {
      "category": "HOLIDAYS & OBSERVANCES",
      "text": "Nevada Day is celebrated on this date; how spooky!",
      "answer": "October 31"
    },
    {
      "category": "BEATLES HITS IN OTHER WORDS",
      "text": "\"Cent Street\"",
      "answer": "\"Penny Lane\""
    },
    {
      "category": "REALLY GRIMM FAIRY TALES",
      "text": "She shoved the wicked old witch of the gingerbread house into the oven & bolted the door",
      "answer": "Gretel"
    },
    {
      "category": "BRIDGES",
      "text": "The Middle East's first suspension bridge, the Mubarak Peace Bridge, opened in 2001 & crosses this canal",
      "answer": "Suez Canal"
    },
    {
      "category": "THE QUESTION IS...",
      "text": "Question that traditionally produces the answer \"Only when I laugh\"",
      "answer": "(When) Does it hurt?"
    },
    {
      "category": "SCIENCE",
      "text": "This \"prefrontal\" medical procedure involves the destruction of sections of the brain's cortex",
      "answer": "lobotomy"
    },
    {
      "category": "HOLIDAYS & OBSERVANCES",
      "text": "By an act of Congress, in 1954 Armistice Day was renamed this",
      "answer": "Veterans Day"
    },
    {
      "category": "BEATLES HITS IN OTHER WORDS",
      "text": "\"Rotate, Then Yell\"",
      "answer": "\"Twist and Shout\""
    },
    {
      "category": "REALLY GRIMM FAIRY TALES",
      "text": "A character in this tale cut off her big toe so that a golden slipper would fit her foot",
      "answer": "\"Cinderella\""
    },
    {
      "category": "BRIDGES",
      "text": "In December 2001 this country opened its first bridge over the Mekong",
      "answer": "Cambodia (Kampuchea)"
    },
    {
      "category": "THE QUESTION IS...",
      "text": "Question posed by Virginia O'Hanlon, age 8, in a letter to a newspaper in 1897",
      "answer": "Is there a Santa Claus?"
    },
    {
      "category": "SCIENCE",
      "text": "This process of making rubber harder & more elastic by heating it with sulfur bears the name of a Roman god",
      "answer": "vulcanization"
    },
    {
      "category": "HOLIDAYS & OBSERVANCES",
      "text": "\"Harambee!\" & \"Habari Gani!\" are phrases used by African Americans during this 7-day celebration",
      "answer": "Kwanzaa"
    },
    {
      "category": "BEATLES HITS IN OTHER WORDS",
      "text": "\"Coupon for Travel\"",
      "answer": "\"Ticket to Ride\""
    },
    {
      "category": "REALLY GRIMM FAIRY TALES",
      "text": "It's the response to \"But Grandmother, what a terrible big mouth you have!\"",
      "answer": "\"The better to eat you, my dear!\""
    },
    {
      "category": "BRIDGES",
      "text": "The Oresund Bridge links Sweden to this country to which it had been unconnected by land for 7,000 yrs.",
      "answer": "Denmark"
    },
    {
      "category": "THE QUESTION IS...",
      "text": "It's the meteorological question that really tall people get really tired of hearing",
      "answer": "How's the weather up there?"
    },
    {
      "category": "SCIENCE",
      "text": "His 1543 book \"Concerning the Revolutions of the Celestial Spheres\" started an astronomical revolution",
      "answer": "Nicholas Copernicus"
    },
    {
      "category": "HOLIDAYS & OBSERVANCES",
      "text": "Think \"fast\"--in 2002 this Muslim holy month began on November 6",
      "answer": "Ramadan"
    },
    {
      "category": "BEATLES HITS IN OTHER WORDS",
      "text": "\"One Difficult 24-Hour Period's Evening\"",
      "answer": "\"A Hard Day's Night\""
    },
    {
      "category": "REALLY GRIMM FAIRY TALES",
      "text": "Her parents gave her to a witch as a newborn; the witch shut her up in a tower at the age of 12",
      "answer": "Rapunzel"
    },
    {
      "category": "BRIDGES",
      "text": "The Chain & Elizabeth Bridges cross this river to connect Buda & Pest",
      "answer": "Danube"
    },
    {
      "category": "THE QUESTION IS...",
      "text": "The last 3 words of the song \"Over the Rainbow\"",
      "answer": "Why can't I?"
    },
    {
      "category": "SCIENCE",
      "text": "The process by which neutral atoms become electrically charged is called this",
      "answer": "ionization"
    },
    {
      "category": "HOLIDAYS & OBSERVANCES",
      "text": "(Sofia of the Clue Crew in front of the Anne Frank House in Amsterdam)  The Anne Frank House here in Amsterdam is open daily except for this holiday",
      "answer": "Yom Kippur"
    },
    {
      "category": "BEATLES HITS IN OTHER WORDS",
      "text": "\"Mistress Ciccone\"",
      "answer": "\"Lady Madonna\""
    },
    {
      "category": "REALLY GRIMM FAIRY TALES",
      "text": "To marry a princess, Hans had to pluck a feather from the tail of this beast that was part lion, part eagle",
      "answer": "griffin"
    },
    {
      "category": "BRIDGES",
      "text": "In 1998 the U.K. lost out to this Asian country for the longest suspension bridge in the world record",
      "answer": "Japan"
    },
    {
      "category": "THE QUESTION IS...",
      "text": "When Jesus said, \"Every one that is of the truth hearest my voice\", Pilate asked him this",
      "answer": "What is truth?"
    }
  ]
}