{
  "title": "Show #9122 - Tuesday, June 11, 2024",
  "date": {
    "day": 11,
    "month": "June",
    "year": 2024
  },
  "clues": [
    {
      "category": "OFF WE \"GO",
      "text": "The tiny population of this huge desert is mostly made up of Mongols & Han Chinese",
      "answer": "the Gobi"
    },
    {
      "category": "FROM THE AD",
      "text": "\"Eatin' good in the neighborhood\"",
      "answer": "Applebee's"
    },
    {
      "category": "NEW TO THEOED",
      "text": "This 2-word term can mean a place you might keep your wallet, or figuratively, someone under your control",
      "answer": "back pocket"
    },
    {
      "category": "THE DREADED OPERA CATEGORY",
      "text": "In Rossini's take on this tale, Alex Trebek's favorite opera, not a fairy but the prince's tutor gets the heroine to the ball",
      "answer": "Cinderella"
    },
    {
      "category": "CLEANUP MEN",
      "text": "The luckiest cleanup hitter on the face of the Earth, Lou Gehrig got to hit fourth just behind this No. 3",
      "answer": "Babe Ruth"
    },
    {
      "category": "AKA",
      "text": "This famous painting is also known as \"La Gioconda\"",
      "answer": "theMona Lisa"
    },
    {
      "category": "OFF WE \"GO",
      "text": "Formerly a city dump, this park in Moscow was named for comrade Maxim in 1932",
      "answer": "Gorky"
    },
    {
      "category": "FROM THE AD",
      "text": "\"For a streak-free shine that lets in more light\"",
      "answer": "Windex"
    },
    {
      "category": "NEW TO THEOED",
      "text": "Seems like this 2-word cardiac-related term for great anguish would've been in sooner than 2024",
      "answer": "broken heart"
    },
    {
      "category": "THE DREADED OPERA CATEGORY",
      "text": "\"Waltz King\" Johann Strauss II also composed the comic opera \"Die Fledermaus\", which translates as this flying animal",
      "answer": "the bat"
    },
    {
      "category": "CLEANUP MEN",
      "text": "He earned a nickname in an October 1977 World Series game, blasting 3 homers on 3 consecutive pitches",
      "answer": "Reggie Jackson"
    },
    {
      "category": "AKA",
      "text": "It's sometimes known as the \"Land of the Inca\"",
      "answer": "Peru"
    },
    {
      "category": "OFF WE \"GO",
      "text": "Near South Bend, Indiana is this city that shares a name with the \"land\" that Joseph told his brothers to settle in",
      "answer": "Goshen"
    },
    {
      "category": "FROM THE AD",
      "text": "A woman wears pink pants & does a TikTok-ish dance pantomiming bodily pain",
      "answer": "Pepto-Bismol"
    },
    {
      "category": "NEW TO THEOED",
      "text": "In the sense \"to sleep briefly\", this verb was already in; 2024 saw it given a new meaning, literally to abduct a pet",
      "answer": "catnap"
    },
    {
      "category": "THE DREADED OPERA CATEGORY",
      "text": "In Wagner's opera about the Valkyries, there are 9 of them, led by this daughter of Wotan",
      "answer": "Brunhild"
    },
    {
      "category": "CLEANUP MEN",
      "text": "Johnny Bench, George Foster & Tony Pérez all cleaned up for this 1976 team",
      "answer": "the Cincinnati Reds"
    },
    {
      "category": "AKA",
      "text": "Kegling is just another name for this sport",
      "answer": "bowling"
    },
    {
      "category": "OFF WE \"GO",
      "text": "Just west of Denver, it had the \"metal\" to be a territorial capital in the 1860s",
      "answer": "Golden, Colorado"
    },
    {
      "category": "FROM THE AD",
      "text": "\"Where are you? You're on a boat with the man your man could smell like\"",
      "answer": "Old Spice"
    },
    {
      "category": "NEW TO THEOED",
      "text": "This unintended silence during a radio or TV broadcast isn't quite as fatal as it sounds",
      "answer": "dead air"
    },
    {
      "category": "THE DREADED OPERA CATEGORY",
      "text": "When Charles Gounod's \"Faust\" is sung in the original French, this evil fiend has accents on all 3 E's in his name",
      "answer": "Méphistophélès"
    },
    {
      "category": "CLEANUP MEN",
      "text": "Good thing the Ilitch family sells lots of pizza; from 2011 to 2018 they paid Victor Martinez $118 million to hit for this A.L. team",
      "answer": "the Tigers"
    },
    {
      "category": "AKA",
      "text": "It might ring a bell that she used the pen name Currer Bell",
      "answer": "Charlotte Brontë"
    },
    {
      "category": "OFF WE \"GO",
      "text": "Sweden's chief seaport, it's also the headquarters of Volvo",
      "answer": "Gothenburg (Göteborg)"
    },
    {
      "category": "FROM THE AD",
      "text": "From the '90s--Woman: \"So what's the paper say about tomorrow?\"  Man: \"Another scorcher!\"  Woman: \"Cool\"",
      "answer": "air conditioning"
    },
    {
      "category": "NEW TO THEOED",
      "text": "This Japanese word means strips of meat or vegetables coated with flour, egg & breadcrumbs & deep fried",
      "answer": "katsu"
    },
    {
      "category": "THE DREADED OPERA CATEGORY",
      "text": "Composer Franco Alfano finished this Asia-set opera after Puccini died",
      "answer": "Turandot"
    },
    {
      "category": "CLEANUP MEN",
      "text": "Willie Stargell, who ruledthisPittsburgh stadium as a cleanup hitter in the '70s, was at the Pirates last game there in 2000",
      "answer": "Three Rivers"
    },
    {
      "category": "AKA",
      "text": "Baking soda, which creates carbon dioxide when mixed with an acid, is also known as this 2-word chemical compound",
      "answer": "sodium bicarbonate"
    }
  ]
}