{
  "title": "Show #2139 - Thursday, December 16, 1993",
  "date": {
    "day": 16,
    "month": "December",
    "year": 1993
  },
  "clues": [
    {
      "category": "CANADA",
      "text": "It's the number of cents in a Canadian dollar—makes sense to us",
      "answer": "100"
    },
    {
      "category": "PHOBIAS",
      "text": "Amathophobia is a fear of this, something everyone returns to & Pledge gets rid of",
      "answer": "dust"
    },
    {
      "category": "BOTANY",
      "text": "Found in a tree's xylem, it's a liquid made up of dissolved mineral salts & sugars",
      "answer": "sap"
    },
    {
      "category": "INVENTORS",
      "text": "Elisha Gray & Alexander Graham Bell contested the invention of this device all the way to the Supreme Court",
      "answer": "the telephone"
    },
    {
      "category": "RHYME TIME",
      "text": "A precious metal that's been around a while",
      "answer": "old gold"
    },
    {
      "category": "THE SPORT PLAYED",
      "text": "Michael Chang,Boris Becker,Gabriela Sabatini",
      "answer": "tennis"
    },
    {
      "category": "CANADA",
      "text": "Dragon boat races are an annual June event in this British Columbia city known for its Asian community",
      "answer": "Vancouver"
    },
    {
      "category": "PHOBIAS",
      "text": "Algophobics fear pain & hedonophobics fear this",
      "answer": "pleasure"
    },
    {
      "category": "BOTANY",
      "text": "Burpee doesn't sell you seeds to grow these vegetables, it sends you eyes",
      "answer": "potatoes"
    },
    {
      "category": "INVENTORS",
      "text": "Scottish inventor John Logie Baird transmitted the first moving picture in this medium",
      "answer": "television"
    },
    {
      "category": "RHYME TIME",
      "text": "Heat Wesson till it bubbles",
      "answer": "boil oil"
    },
    {
      "category": "THE SPORT PLAYED",
      "text": "Barry Sanders,Jim McMahon,Eric Dickerson",
      "answer": "football"
    },
    {
      "category": "CANADA",
      "text": "The motto of this Canadian province is \"Je me souviens\", which means \"I remember\"",
      "answer": "Quebec"
    },
    {
      "category": "PHOBIAS",
      "text": "Chionophobics fear flakes of this",
      "answer": "snow"
    },
    {
      "category": "BOTANY",
      "text": "The anther is usually made up of 4 of these sacs",
      "answer": "pollen sacs"
    },
    {
      "category": "INVENTORS",
      "text": "Joseph Bramah invented several machine tools to make his \"pickproof\" type of this device",
      "answer": "a lock"
    },
    {
      "category": "RHYME TIME",
      "text": "A box with the pattern of a Highland clan",
      "answer": "a tartan carton"
    },
    {
      "category": "THE SPORT PLAYED",
      "text": "James Worthy,Karl Malone,Isiah Thomas",
      "answer": "basketball"
    },
    {
      "category": "CANADA",
      "text": "Canada's beautiful National Gallery isn't far from the Parliament buildings in this city",
      "answer": "Ottawa"
    },
    {
      "category": "PHOBIAS",
      "text": "An erg is a unit of this; ergo, ergophobia is a fear of it",
      "answer": "work"
    },
    {
      "category": "BOTANY",
      "text": "Michigan, New Jersey & North Carolina grow the Highbush variety of this bright berry",
      "answer": "the blueberry"
    },
    {
      "category": "INVENTORS",
      "text": "In the 1790s Richard Trevithick invented the first high-pressure type of this engine",
      "answer": "a steam engine"
    },
    {
      "category": "RHYME TIME",
      "text": "A weighty tax",
      "answer": "a heavy levy"
    },
    {
      "category": "THE SPORT PLAYED",
      "text": "Cecil Fielder,Roger Clemens,Dennis Eckersley",
      "answer": "baseball"
    },
    {
      "category": "CANADA",
      "text": "This Nova Scotia city is the largest in Canada's Atlantic provinces",
      "answer": "Halifax"
    },
    {
      "category": "PHOBIAS",
      "text": "Ancraophobics wouldn't like to find the answer, my friend, here",
      "answer": "the wind"
    },
    {
      "category": "BOTANY",
      "text": "Some of these plants, like cacti, store water in their stems; others use their leaves",
      "answer": "succulents"
    },
    {
      "category": "INVENTORS",
      "text": "Charles Kettering, inventor of an electric cash register, also co-founded this cancer institute",
      "answer": "Sloan-Kettering"
    },
    {
      "category": "RHYME TIME",
      "text": "A Viking equestrian",
      "answer": "a Norseman horseman"
    },
    {
      "category": "THE SPORT PLAYED",
      "text": "Betsy King,Beth Daniel,Patty Sheehan",
      "answer": "golf"
    }
  ]
}