{
  "title": "Show #6723 - Wednesday, December 4, 2013",
  "date": {
    "day": 4,
    "month": "December",
    "year": 2013
  },
  "clues": [
    {
      "category": "HAVE A DRINK",
      "text": "Some recipes for a hurricane call for both the dark & light types of this",
      "answer": "rum"
    },
    {
      "category": "GUINNESS",
      "text": "A grooming brush & ham slices helped a British feline set the record for loudest this by a domestic cat, 67.7 decibels",
      "answer": "a purr"
    },
    {
      "category": "FINLANDIA",
      "text": "The Evangelical variety of this major Protestant denomination is the religion most widely practiced by Finns",
      "answer": "Lutheran"
    },
    {
      "category": "CANADIAN CLUB",
      "text": "Rachel McAdams & this co-star of \"The Notebook\" were both born in London, Ontario",
      "answer": "Ryan Gosling"
    },
    {
      "category": "ON THE ROCKS",
      "text": "More than 7 billion tons of this black or brown energy-producing rock are used worldwide every year",
      "answer": "coal"
    },
    {
      "category": "FEELING TIP\"SY",
      "text": "When having photos printed, you usually have your choice between matte or this finish",
      "answer": "glossy"
    },
    {
      "category": "HAVE A DRINK",
      "text": "Aged for 40 years or more, Armagnac is a type of this made in France",
      "answer": "brandy"
    },
    {
      "category": "GUINNESS",
      "text": "2 guys kept a rally going for over 8 hours in this indoor sport",
      "answer": "table tennis"
    },
    {
      "category": "FINLANDIA",
      "text": "In the 1920s this Finnish track athlete won 9 Olympic gold medals & 3 silvers",
      "answer": "(Paavo) Nurmi"
    },
    {
      "category": "CANADIAN CLUB",
      "text": "Canadian Cobie Smulders plays Canadian Robin Scherbatsky (aka Robin Sparkles) on this sitcom",
      "answer": "How I Met Your Mother"
    },
    {
      "category": "ON THE ROCKS",
      "text": "Consisting of tiny crystals of quartz, this rock that provides a spark was utilized in early firearms",
      "answer": "a flint"
    },
    {
      "category": "FEELING TIP\"SY",
      "text": "In January 1431 Joan of Arc went on trial for witchcraft & this",
      "answer": "heresy"
    },
    {
      "category": "HAVE A DRINK",
      "text": "According to its website, it's the world's top-selling cream liqueur brand",
      "answer": "Baileys"
    },
    {
      "category": "GUINNESS",
      "text": "At a 2009 U.K. competition, Terry Burrows & his squeegee cleaned 3 45 x 45 in. these in 9.14 seconds",
      "answer": "windows"
    },
    {
      "category": "FINLANDIA",
      "text": "One of the 2 countries that took turns controlling Finland from the 1100s to its 1917 independence",
      "answer": "Russia (or Sweden)"
    },
    {
      "category": "CANADIAN CLUB",
      "text": "Born in Vancouver, he was People's Sexiest Man Alive in 2010 & the Green Lantern in 2011",
      "answer": "Ryan Reynolds"
    },
    {
      "category": "ON THE ROCKS",
      "text": "Tampa's \"Sinkhole Alley\" is caused in part by acidic water eroding this porous \"stone\"",
      "answer": "limestone"
    },
    {
      "category": "FEELING TIP\"SY",
      "text": "During Prohibition New York's famed 21 Club operated as one of these illegal bars",
      "answer": "a speakeasy"
    },
    {
      "category": "HAVE A DRINK",
      "text": "Ads for this Kentucky bourbon say, \"Give 'em the Bird\"",
      "answer": "Wild Turkey"
    },
    {
      "category": "GUINNESS",
      "text": "Just over a foot across at one point, the Spreuerhofstrasse in Reutlingen is the world's narrowest this",
      "answer": "a street"
    },
    {
      "category": "FINLANDIA",
      "text": "In 2013 Microsoft agreed to buy this Finnish company's mobile phone business for $7.2 billion",
      "answer": "Nokia"
    },
    {
      "category": "ON THE ROCKS",
      "text": "The most common plutonic rock of the Earth's crust, it is big in tombstones",
      "answer": "granite"
    },
    {
      "category": "FEELING TIP\"SY",
      "text": "Literary genre of Piers Anthony & Robert Jordan",
      "answer": "fantasy"
    },
    {
      "category": "HAVE A DRINK",
      "text": "It's the rhyming name of the tequila created by Sammy Hagar to serve at his Mexican cantina",
      "answer": "Cabo Wabo"
    },
    {
      "category": "GUINNESS",
      "text": "Edward Watson's dog Rose caught 7 of these one at a time, keeping them all in her mouth at once",
      "answer": "frisbees"
    },
    {
      "category": "FINLANDIA",
      "text": "Before Finland was free, the musical work \"Finlandia\" by this native son was banned for arousing patriotism",
      "answer": "(Jean) Sibelius"
    },
    {
      "category": "CANADIAN CLUB",
      "text": "In 2003 this British Columbia crooner gave us his jazzy takes on standards like \"Fever\" & \"The Way You Look Tonight\"",
      "answer": "Michael Bublé"
    },
    {
      "category": "ON THE ROCKS",
      "text": "TheAmar Singh Gateat the Fort of Agra, India, is made ofthissecond-most-common sedimentary rock",
      "answer": "sandstone"
    },
    {
      "category": "FEELING TIP\"SY",
      "text": "This adjective describes the \"Chaperone\" in the title of a 2006 Tony-winning musical",
      "answer": "Drowsy"
    },
    {
      "category": "BRITISH NOVELS' FIRST LINES",
      "text": "A Christie mystery: \"It was 5:00 on a winter's morning in Syria.  Alongside the platform at Aleppo stood the train...\"",
      "answer": "Murder on the Orient Express"
    },
    {
      "category": "WRAP MUSIC",
      "text": "\"It's The End Of The World As We Know It\", this band sang in 1987 (& they felt fine)",
      "answer": "R.E.M."
    },
    {
      "category": "ALL \"GON",
      "text": "Large percussive disk",
      "answer": "a gong"
    },
    {
      "category": "AFFLICTIONS OF YORE",
      "text": "In addition to black lung, these workers were regularly afflicted by stink damp & silicosis",
      "answer": "coal miners"
    },
    {
      "category": "AFTER I LOST THE PRESIDENTIAL ELECTION",
      "text": "I helped form the Alliance for Climate Protection & appeared as myself on \"Futurama\"",
      "answer": "Al Gore"
    },
    {
      "category": "BRITISH NOVELS' FIRST LINES",
      "text": "1813: \"It is a truth universally acknowledged, that a single man in possession of a... fortune, must be in want of a wife\"",
      "answer": "Pride and Prejudice"
    },
    {
      "category": "WRAP MUSIC",
      "text": "In a 1989 hit, Don Henley lamented \"The End Of\" this--sounds like a song of experience",
      "answer": "\"The Innocence\""
    },
    {
      "category": "ALL \"GON",
      "text": "It's the only mythical creature in the Chinese zodiac",
      "answer": "a dragon"
    },
    {
      "category": "AFFLICTIONS OF YORE",
      "text": "Canine madness have you foaming?  Then you've come down with this unfortunate sickness",
      "answer": "rabies"
    },
    {
      "category": "AFTER I LOST THE PRESIDENTIAL ELECTION",
      "text": "I practiced law in Los Angeles, then lost a run for statewide office; I wasn't done with politics, though",
      "answer": "Richard Nixon"
    },
    {
      "category": "BRITISH NOVELS' FIRST LINES",
      "text": "E.M. Forster: \"Except for the Marabar Caves... the city of Chandrapore presents nothing extraordinary\"",
      "answer": "A Passage to India"
    },
    {
      "category": "THE CALENDAR",
      "text": "This calendar was introduced in the 1790s",
      "answer": "the French Revolutionary calendar"
    },
    {
      "category": "WRAP MUSIC",
      "text": "This coach on \"The Voice\" won a 2010 Grammy for \"Forget You\", which has a colorful alternate title",
      "answer": "CeeLo Green"
    },
    {
      "category": "ALL \"GON",
      "text": "Crazy a la Hunter S. Thompson",
      "answer": "gonzo"
    },
    {
      "category": "AFFLICTIONS OF YORE",
      "text": "Illuminating gas poisoning had nothing to do with that second helping of pudding, but rather this gas, CO",
      "answer": "carbon monoxide"
    },
    {
      "category": "AFTER I LOST THE PRESIDENTIAL ELECTION",
      "text": "I stayed on as gov. of N.Y. & turned down an offer to be Chief Justice of the U.S.; I also learned not to believe newspapers",
      "answer": "(Thomas) Dewey"
    },
    {
      "category": "BRITISH NOVELS' FIRST LINES",
      "text": "1962: \"'What's it going to be then, eh?'  There was me, that is Alex, and my three droogs\"",
      "answer": "A Clockwork Orange"
    },
    {
      "category": "THE CALENDAR",
      "text": "The Celtic word Samhain can refer to this month or to a festival on the first day of it",
      "answer": "November"
    },
    {
      "category": "WRAP MUSIC",
      "text": "In 1992 Boyz II Men reached the \"End Of\" this, & it took them to No. 1",
      "answer": "\"The Road\""
    },
    {
      "category": "ALL \"GON",
      "text": "Ancient supercontinent",
      "answer": "Gondwana (or Gondwanaland)"
    },
    {
      "category": "AFFLICTIONS OF YORE",
      "text": "\"Hardening of the liver\" is what we now call this of the liver",
      "answer": "cirrhosis"
    },
    {
      "category": "AFTER I LOST THE PRESIDENTIAL ELECTION",
      "text": "Having lost control of my newspaper as well as the vote, I died Nov. 29, 1872, before the electors even met",
      "answer": "Horace Greeley"
    },
    {
      "category": "BRITISH NOVELS' FIRST LINES",
      "text": "Edward Bulwer-Lytton: The often parodied \"It was a dark and stormy night; the rain fell in torrents\"",
      "answer": "Paul Clifford"
    },
    {
      "category": "THE CALENDAR",
      "text": "John Wilkes Booth saw himself as a dictator-slayer, so his original target date was April 13, which is this on the Roman calendar",
      "answer": "the Ides of April"
    },
    {
      "category": "WRAP MUSIC",
      "text": "In a Bob Dylan song title, this 4-word declaration of finality precedes \"Baby Blue\"",
      "answer": "\"It's All Over Now\""
    },
    {
      "category": "ALL \"GON",
      "text": "A line in the Song of Solomon requests, \"stay me with\" these drinking vessels",
      "answer": "a flagon"
    },
    {
      "category": "AFFLICTIONS OF YORE",
      "text": "\"The horrors\" was a term for the hallucinations experienced during this \"shaking\" state of alcohol withdrawal",
      "answer": "the DTs"
    },
    {
      "category": "AFTER I LOST THE PRESIDENTIAL ELECTION",
      "text": "I helped my wife run for president & later, successfully, for the Senate",
      "answer": "(Robert) Dole"
    }
  ]
}